rembg_serverless/__init__.py
rembg_serverless/_version.py
rembg_serverless/bg.py
rembg_serverless/session_base.py
rembg_serverless/session_factory.py
rembg_serverless/session_simple.py
rembg_serverless/u2net.onnx
rembg_serverless/sessions/__init__.py
rembg_serverless/sessions/base.py
rembg_serverless/sessions/birefnet_cod.py
rembg_serverless/sessions/birefnet_dis.py
rembg_serverless/sessions/birefnet_general.py
rembg_serverless/sessions/birefnet_general_lite.py
rembg_serverless/sessions/birefnet_hrsod.py
rembg_serverless/sessions/birefnet_massive.py
rembg_serverless/sessions/birefnet_portrait.py
rembg_serverless/sessions/dis_anime.py
rembg_serverless/sessions/dis_general_use.py
rembg_serverless/sessions/silueta.py
rembg_serverless/sessions/u2net.py
rembg_serverless/sessions/u2net_human_seg.py
rembg_serverless/sessions/u2netp.onnx
rembg_serverless/sessions/u2netp.py
rembg_serverless-0.1.3.5.dist-info/LICENSE.txt
rembg_serverless-0.1.3.5.dist-info/METADATA
rembg_serverless-0.1.3.5.dist-info/WHEEL
rembg_serverless-0.1.3.5.dist-info/top_level.txt
rembg_serverless-0.1.3.5.dist-info/RECORD
