Metadata-Version: 2.1
Name: rembg-serverless
Version: 0.1.3.5
Summary: Remove image background
Home-page: https://github.com/rnag/rembg-aws-lambda
Author: Daniel Gatis
Author-email: danielgatis@gmail.com
Keywords: remove,background,u2net
Classifier: License :: OSI Approved :: MIT License
Classifier: Topic :: Scientific/Engineering
Classifier: Topic :: Scientific/Engineering :: Mathematics
Classifier: Topic :: Scientific/Engineering :: Artificial Intelligence
Classifier: Topic :: Software Development
Classifier: Topic :: Software Development :: Libraries
Classifier: Topic :: Software Development :: Libraries :: Python Modules
Classifier: Programming Language :: Python
Classifier: Programming Language :: Python :: 3 :: Only
Classifier: Programming Language :: Python :: 3.8
Classifier: Programming Language :: Python :: 3.9
Classifier: Programming Language :: Python :: 3.10
Requires-Python: >3.7, <3.12
License-File: LICENSE.txt
Requires-Dist: numpy ~=1.24.2
Requires-Dist: onnxruntime ~=1.15.0
Requires-Dist: pillow ~=9.3.0
Provides-Extra: gpu
Requires-Dist: onnxruntime-gpu ; extra == 'gpu'
